openfertility/__init__.py
openfertility/io.py
openfertility/datasets/__init__.py
openfertility/datasets/blasto2k.py
openfertility/datasets/utils.py
openfertility/display/__init__.py
openfertility/display/img.py
openfertility/display/plot.py
openfertility-0.1.0.dist-info/LICENSE
openfertility-0.1.0.dist-info/METADATA
openfertility-0.1.0.dist-info/WHEEL
openfertility-0.1.0.dist-info/top_level.txt
openfertility-0.1.0.dist-info/RECORD
