Metadata-Version: 2.1
Name: openfertility
Version: 0.1.0
Summary: Machine learning and data analysis for fertility
Home-page: https://github.com/delestro/openfertility
Author: Felipe Delestro
Author-email: delestro@gmail.com
Classifier: Development Status :: 1 - Planning
Classifier: Intended Audience :: Developers
Classifier: Intended Audience :: Science/Research
Classifier: Intended Audience :: Healthcare Industry
Classifier: License :: OSI Approved :: MIT License
Classifier: Natural Language :: English
Classifier: Programming Language :: Python :: 3
License-File: LICENSE
Requires-Dist: pandas
Requires-Dist: numpy
Requires-Dist: torch
Requires-Dist: scikit-learn
Requires-Dist: matplotlib
